LICENSE
MANIFEST.in
README.rst
pidly.py
setup.py
pIDLy.egg-info/PKG-INFO
pIDLy.egg-info/SOURCES.txt
pIDLy.egg-info/dependency_links.txt
pIDLy.egg-info/requires.txt
pIDLy.egg-info/top_level.txt