Metadata-Version: 1.1
Name: pIDLy
Version: 0.2.5
Summary: IDL within Python
Home-page: https://github.com/anthonyjsmith/pIDLy
Author: Anthony Smith
Author-email: anthonysmith80@gmail.com
License: MIT
Platform: UNKNOWN
Classifier: Development Status :: 3 - Alpha
Classifier: Intended Audience :: Science/Research
Classifier: Programming Language :: Other
Classifier: License :: OSI Approved :: MIT License
Requires: NumPy
Requires: Pexpect
